habiter/__init__.py
habiter/api/__init__.py
habiter/api/export.py
habiter/internal/__init__.py
habiter/internal/cli.py
habiter/internal/math.py
habiter/internal/run.py
habiter/internal/commands/__init__.py
habiter/internal/commands/_utils.py
habiter/internal/commands/add.py
habiter/internal/commands/list.py
habiter/internal/commands/remove.py
habiter/internal/commands/reset.py
habiter/internal/commands/tally.py
habiter/internal/file/__init__.py
habiter/internal/file/creator.py
habiter/internal/file/operations.py
habiter/internal/file/updater.py
habiter/internal/utils/__init__.py
habiter/internal/utils/consts.py
habiter/internal/utils/messenger.py
habiter-0.8.0.dist-info/LICENSE
habiter-0.8.0.dist-info/METADATA
habiter-0.8.0.dist-info/WHEEL
habiter-0.8.0.dist-info/entry_points.txt
habiter-0.8.0.dist-info/top_level.txt
habiter-0.8.0.dist-info/RECORD
