Metadata-Version: 2.1
Name: habiter
Version: 0.8.0
Summary: Quantifiy and keep tabs on habits.
Home-page: https://github.com/kemzeb/habiter
Author: Kemal Zebari
License: MIT
Keywords: productivity,cli
Platform: UNKNOWN
Classifier: License :: OSI Approved :: MIT License
Classifier: Programming Language :: Python :: 3
Requires-Python: >=3.9
License-File: LICENSE
Requires-Dist: click (>=8.1.3)
Requires-Dist: platformdirs (>=3.2.0)
Provides-Extra: dev
Requires-Dist: habiter[style] ; extra == 'dev'
Requires-Dist: pytest (>=7.2.2) ; extra == 'dev'
Requires-Dist: twine (>=4.0.2) ; extra == 'dev'
Provides-Extra: style
Requires-Dist: black (>=23.3.0) ; extra == 'style'
Requires-Dist: flake8 (>=6.0.0) ; extra == 'style'
Requires-Dist: isort (>=5.12.0) ; extra == 'style'
